Metadata-Version: 2.1
Name: x-rand
Version: 0.12
Summary: Random Problem Creation for edX
Home-page: https://github.com/connor-makowski/x_rand
Download-URL: https://github.com/connor-makowski/x_rand/blob/master/dist/x_rand-0.12.tar.gz
Author: Connor Makowski
Author-email: connor.m.makowski@gmail.com
License: MIT
Keywords: x_rand,edX,randomization,random,cheating,prevention,detection
Classifier: Development Status :: 3 - Alpha
Classifier: Intended Audience :: Developers
Classifier: Topic :: Software Development :: Build Tools
Classifier: License :: OSI Approved :: MIT License
Classifier: Programming Language :: Python :: 3
License-File: LICENSE
